pandas_parallel_apply/__init__.py
pandas_parallel_apply/data_frame_parallel.py
pandas_parallel_apply/groupby_parallel.py
pandas_parallel_apply/logger.py
pandas_parallel_apply/series_parallel.py
pandas_parallel_apply/utils.py
pandas_parallel_apply-2.2.dist-info/LICENSE
pandas_parallel_apply-2.2.dist-info/METADATA
pandas_parallel_apply-2.2.dist-info/WHEEL
pandas_parallel_apply-2.2.dist-info/top_level.txt
pandas_parallel_apply-2.2.dist-info/RECORD
