Metadata-Version: 2.1
Name: pandas-parallel-apply
Version: 2.2
Summary: Wrapper for df and df[col].apply parallelized
Home-page: https://gitlab.com/meehai/pandas-parallel-apply
License: WTFPL
Requires-Python: >=3.8
License-File: LICENSE
